{"box_data": [{"position": {"minX": 332.5, "minY": 452.0, "maxX": 371.0, "maxY": 516.0}, "class_id": 0, "box_caption": "badge 0.892", "scores": {"class_score": 0.89208984375}, "domain": "pixel"}, {"position": {"minX": 99.5, "minY": 361.0, "maxX": 121.875, "maxY": 416.0}, "class_id": 0, "box_caption": "badge 0.297", "scores": {"class_score": 0.29736328125}, "domain": "pixel"}, {"position": {"minX": 243.25, "minY": 386.0, "maxX": 278.25, "maxY": 435.0}, "class_id": 0, "box_caption": "badge 0.041", "scores": {"class_score": 0.04107666015625}, "domain": "pixel"}, {"position": {"minX": 285.5, "minY": 415.5, "maxX": 439.0, "maxY": 563.0}, "class_id": 0, "box_caption": "badge 0.026", "scores": {"class_score": 0.026458740234375}, "domain": "pixel"}, {"position": {"minX": 529.0, "minY": 492.75, "maxX": 599.0, "maxY": 545.0}, "class_id": 0, "box_caption": "badge 0.006", "scores": {"class_score": 0.00609588623046875}, "domain": "pixel"}, {"position": {"minX": 49.9375, "minY": 169.0, "maxX": 109.5625, "maxY": 211.25}, "class_id": 0, "box_caption": "badge 0.004", "scores": {"class_score": 0.003635406494140625}, "domain": "pixel"}, {"position": {"minX": 462.0, "minY": 152.875, "maxX": 512.0, "maxY": 193.375}, "class_id": 0, "box_caption": "badge 0.003", "scores": {"class_score": 0.003147125244140625}, "domain": "pixel"}, {"position": {"minX": 40.0625, "minY": 147.0, "maxX": 112.5625, "maxY": 230.25}, "class_id": 0, "box_caption": "badge 0.003", "scores": {"class_score": 0.0028667449951171875}, "domain": "pixel"}, {"position": {"minX": 137.125, "minY": 287.25, "maxX": 398.0, "maxY": 522.0}, "class_id": 0, "box_caption": "badge 0.002", "scores": {"class_score": 0.0024051666259765625}, "domain": "pixel"}, {"position": {"minX": 538.0, "minY": 512.0, "maxX": 593.0, "maxY": 547.0}, "class_id": 0, "box_caption": "badge 0.002", "scores": {"class_score": 0.0016546249389648438}, "domain": "pixel"}, {"position": {"minX": 189.25, "minY": 154.0, "maxX": 240.75, "maxY": 197.0}, "class_id": 0, "box_caption": "badge 0.001", "scores": {"class_score": 0.0014781951904296875}, "domain": "pixel"}, {"position": {"minX": 471.0, "minY": 435.75, "maxX": 651.0, "maxY": 588.0}, "class_id": 0, "box_caption": "badge 0.001", "scores": {"class_score": 0.0012941360473632812}, "domain": "pixel"}, {"position": {"minX": 523.0, "minY": 483.0, "maxX": 580.0, "maxY": 546.0}, "class_id": 0, "box_caption": "badge 0.001", "scores": {"class_score": 0.0010900497436523438}, "domain": "pixel"}, {"position": {"minX": -12.5625, "minY": 121.875, "maxX": 170.5, "maxY": 277.0}, "class_id": 0, "box_caption": "badge 0.001", "scores": {"class_score": 0.0010862350463867188}, "domain": "pixel"}], "class_labels": {"0": "badge"}}