{"box_data": [{"position": {"minX": 537.0, "minY": 400.25, "maxX": 586.0, "maxY": 437.75}, "class_id": 0, "box_caption": "badge 0.005", "scores": {"class_score": 0.005138397216796875}, "domain": "pixel"}, {"position": {"minX": 657.5, "minY": 413.75, "maxX": 672.5, "maxY": 463.25}, "class_id": 0, "box_caption": "badge 0.003", "scores": {"class_score": 0.003429412841796875}, "domain": "pixel"}, {"position": {"minX": 657.0, "minY": 334.75, "maxX": 673.0, "maxY": 380.75}, "class_id": 0, "box_caption": "badge 0.003", "scores": {"class_score": 0.003185272216796875}, "domain": "pixel"}, {"position": {"minX": 658.0, "minY": 398.0, "maxX": 673.0, "maxY": 451.5}, "class_id": 0, "box_caption": "badge 0.003", "scores": {"class_score": 0.0028781890869140625}, "domain": "pixel"}, {"position": {"minX": 530.5, "minY": 399.0, "maxX": 586.5, "maxY": 458.0}, "class_id": 0, "box_caption": "badge 0.002", "scores": {"class_score": 0.0020503997802734375}, "domain": "pixel"}, {"position": {"minX": 212.0, "minY": 91.3125, "maxX": 259.25, "maxY": 149.125}, "class_id": 0, "box_caption": "badge 0.001", "scores": {"class_score": 0.0012645721435546875}, "domain": "pixel"}, {"position": {"minX": 658.5, "minY": 380.5, "maxX": 672.5, "maxY": 437.0}, "class_id": 0, "box_caption": "badge 0.001", "scores": {"class_score": 0.001239776611328125}, "domain": "pixel"}, {"position": {"minX": 312.0, "minY": 202.5, "maxX": 333.0, "maxY": 227.75}, "class_id": 0, "box_caption": "badge 0.001", "scores": {"class_score": 0.001220703125}, "domain": "pixel"}], "class_labels": {"0": "badge"}}