{
    "os": "Linux-5.13.0-52-generic-x86_64-with-glibc2.31",
    "python": "3.9.7",
    "heartbeatAt": "2022-07-09T11:52:19.722121",
    "startedAt": "2022-07-09T11:52:18.196835",
    "docker": null,
    "gpu": "NVIDIA GeForce RTX 2080",
    "gpu_count": 1,
    "cpu_count": 16,
    "cuda": null,
    "args": [
        "--img",
        "640",
        "--batch",
        "-1",
        "--epochs",
        "500",
        "--data",
        "dataset.yaml",
        "--weights",
        "yolov5s.pt"
    ],
    "state": "running",
    "program": "/home/sirius/Tracking/yolov5/train.py",
    "codePath": "yolov5/train.py",
    "git": {
        "remote": "https://github.com/br0fire/Tracking.git",
        "commit": "33a4f6bd8f6a0c74cf76dabb040ce8d2e0036baf"
    },
    "email": "tgrozny@yandex.ru",
    "root": "/home/sirius/Tracking",
    "host": "sirius-OptiPlex-7071",
    "username": "sirius",
    "executable": "/home/sirius/anaconda3/bin/python3"
}
